bcml/__init__.py
bcml_ai-0.0.3.dist-info/METADATA
bcml_ai-0.0.3.dist-info/WHEEL
bcml_ai-0.0.3.dist-info/licenses/LICENSE
bcml_ai-0.0.3.dist-info/RECORD
