Metadata-Version: 2.4
Name: bcml-ai
Version: 0.0.3
Summary: **BCML's** official Python library for loading BCML AI models.
Project-URL: Homepage, https://github.com/bcml-ai/bcml-ai/
Author-email: Darin Tanner <bcml@example.com>
License: GNU Affero General Public License v3.0 (AGPL-3.0-only)
License-File: LICENSE
Classifier: Development Status :: 3 - Alpha
Classifier: License :: OSI Approved :: GNU Affero General Public License v3
Classifier: Operating System :: OS Independent
Classifier: Programming Language :: Python :: 3
Classifier: Programming Language :: Python :: 3 :: Only
Requires-Python: >=3.9
